[
    {
        "content": "<p>I think the projects suggested so far were</p>\n<p>1) State the heat equation. Prove that that the standard convolution solution is a solution. Prove that this is the only solution.<br>\n2) Implerment the method of characteristics<br>\n3) State Navier-Stokes<br>\n4) Doob Lp inequality<br>\n5) Local martingales</p>\n<p>I personally think that any project of the form \"state something\" is very hard for beginners. It's far easier for an expert to state the questions and then the beginners to try and prove it.</p>",
        "id": 543635600,
        "sender_full_name": "Kevin Buzzard",
        "timestamp": 1759878816
    },
    {
        "content": "<p>(6) State the wave equation (using the abstract formalism from the talk, or by hand)</p>",
        "id": 543637813,
        "sender_full_name": "Michael Rothgang",
        "timestamp": 1759880509
    },
    {
        "content": "<p>(7) finite speed of propagation for the wave equation</p>",
        "id": 543637920,
        "sender_full_name": "Michael Rothgang",
        "timestamp": 1759880594
    },
    {
        "content": "<p>Can you state (7)? I am concerned that many of these projects involve (and in some cases are nothing but) \"state something\"</p>",
        "id": 543637955,
        "sender_full_name": "Kevin Buzzard",
        "timestamp": 1759880634
    },
    {
        "content": "<p>Once a PDE expert tells me what the statement is, I'm very happy to help with that part.</p>",
        "id": 543638020,
        "sender_full_name": "Michael Rothgang",
        "timestamp": 1759880694
    },
    {
        "content": "<p>SLMath have shut off the Zoom feed BTW (so I'm going to sleep now and will stop bothering you!)</p>",
        "id": 543638024,
        "sender_full_name": "Kevin Buzzard",
        "timestamp": 1759880698
    },
    {
        "content": "<p>The system is a massive learning curve and it's very easy for us as experts to forget this. I'm wondering whether e.g. stating the canonical solution to the wave equation (given initial conditions) is something which should be done by Remy and then proving that it is a solution is perhaps more viable for the participants</p>",
        "id": 543638164,
        "sender_full_name": "Kevin Buzzard",
        "timestamp": 1759880803
    },
    {
        "content": "<p>This will no doubt involve things like differentiating under the integral etc, but without an expert stating the problem there's a risk that the problem gets stated incorrectly, making it much harder to solve</p>",
        "id": 543638249,
        "sender_full_name": "Kevin Buzzard",
        "timestamp": 1759880874
    },
    {
        "content": "<p>Hi. I am trying to verify the solution to the heat equation -- project 1.</p>\n<div class=\"codehilite\" data-code-language=\"Lean4\"><pre><span></span><code><span class=\"kn\">import</span><span class=\"w\"> </span><span class=\"n\">Mathlib</span><span class=\"bp\">.</span><span class=\"n\">Probability</span><span class=\"bp\">.</span><span class=\"n\">Distributions</span><span class=\"bp\">.</span><span class=\"n\">Gaussian</span><span class=\"bp\">.</span><span class=\"n\">Real</span>\n<span class=\"kn\">open</span><span class=\"w\"> </span><span class=\"n\">ProbabilityTheory</span>\n\n<span class=\"kn\">noncomputable</span>\n<span class=\"kn\">def</span><span class=\"w\"> </span><span class=\"n\">f</span><span class=\"w\"> </span><span class=\"o\">(</span><span class=\"n\">t</span><span class=\"o\">:</span><span class=\"n\">ℝ</span><span class=\"o\">)</span><span class=\"w\"> </span><span class=\"n\">x</span><span class=\"w\"> </span><span class=\"o\">:=</span><span class=\"w\"> </span><span class=\"k\">if</span><span class=\"w\"> </span><span class=\"n\">ht</span><span class=\"w\"> </span><span class=\"o\">:</span><span class=\"w\"> </span><span class=\"mi\">0</span><span class=\"w\"> </span><span class=\"bp\">&lt;</span><span class=\"w\"> </span><span class=\"n\">t</span><span class=\"w\"> </span><span class=\"k\">then</span><span class=\"w\"> </span><span class=\"n\">gaussianPDFReal</span><span class=\"w\"> </span><span class=\"mi\">0</span><span class=\"w\"> </span><span class=\"bp\">⟨</span><span class=\"n\">t</span><span class=\"o\">,</span><span class=\"w\"> </span><span class=\"n\">le_of_lt</span><span class=\"w\"> </span><span class=\"n\">ht</span><span class=\"bp\">⟩</span><span class=\"w\"> </span><span class=\"n\">x</span><span class=\"w\"> </span><span class=\"k\">else</span><span class=\"w\"> </span><span class=\"mi\">0</span>\n\n<span class=\"kn\">lemma</span><span class=\"w\"> </span><span class=\"n\">deriv_t</span><span class=\"w\"> </span><span class=\"o\">{</span><span class=\"n\">x</span><span class=\"w\"> </span><span class=\"o\">:</span><span class=\"w\"> </span><span class=\"n\">ℝ</span><span class=\"o\">}</span><span class=\"w\"> </span><span class=\"o\">(</span><span class=\"n\">ht</span><span class=\"w\"> </span><span class=\"o\">:</span><span class=\"w\"> </span><span class=\"n\">t</span><span class=\"w\"> </span><span class=\"bp\">&gt;</span><span class=\"w\"> </span><span class=\"mi\">0</span><span class=\"o\">)</span><span class=\"w\"> </span><span class=\"o\">:</span><span class=\"w\"> </span><span class=\"n\">deriv</span><span class=\"w\"> </span><span class=\"o\">(</span><span class=\"k\">fun</span><span class=\"w\"> </span><span class=\"n\">t</span><span class=\"w\"> </span><span class=\"bp\">=&gt;</span><span class=\"w\"> </span><span class=\"n\">f</span><span class=\"w\"> </span><span class=\"n\">t</span><span class=\"w\"> </span><span class=\"n\">x</span><span class=\"o\">)</span><span class=\"w\"> </span><span class=\"n\">t</span><span class=\"w\"> </span><span class=\"bp\">=</span><span class=\"w\"> </span><span class=\"o\">(</span><span class=\"n\">f</span><span class=\"w\"> </span><span class=\"n\">t</span><span class=\"w\"> </span><span class=\"n\">x</span><span class=\"o\">)</span><span class=\"w\"> </span><span class=\"bp\">*</span><span class=\"w\"> </span><span class=\"o\">(</span><span class=\"bp\">-</span><span class=\"mi\">1</span><span class=\"bp\">/</span><span class=\"n\">t</span><span class=\"w\"> </span><span class=\"bp\">+</span><span class=\"w\"> </span><span class=\"n\">x</span><span class=\"bp\">^</span><span class=\"mi\">2</span><span class=\"bp\">/</span><span class=\"n\">t</span><span class=\"bp\">^</span><span class=\"mi\">2</span><span class=\"o\">)</span><span class=\"w\"> </span><span class=\"o\">:=</span><span class=\"w\"> </span><span class=\"k\">by</span>\n<span class=\"w\">  </span><span class=\"n\">unfold</span><span class=\"w\"> </span><span class=\"n\">f</span>\n<span class=\"w\">  </span><span class=\"n\">simp</span><span class=\"w\"> </span><span class=\"o\">[</span><span class=\"n\">ht</span><span class=\"o\">]</span><span class=\"w\"> </span><span class=\"c1\">-- does not simp under binder `deriv`</span>\n</code></pre></div>\n<p>I have two questions:</p>\n<ol>\n<li>Is this the right way to circumvent the fact that <code>deriv</code> expects a normed field but <code>gaussianPDFReal</code> takes a <code>NNReal</code>?</li>\n<li>How to simp <code>f</code> under the binder <code>deriv</code>?</li>\n</ol>",
        "id": 543664599,
        "sender_full_name": "Vasily Ilin",
        "timestamp": 1759902803
    },
    {
        "content": "<p><span class=\"user-mention\" data-user-id=\"634338\">@Michael Rothgang</span> Suppose u = u(x, t): ℝⁿ × ℝ → ℝ is C² and satisfies the <strong>wave equation</strong> ∂²u/∂t² = ∇²u.</p>\n<p><strong>Finite speed of propagation:</strong> If u(x, 0) = 0 and ∂u/∂t(x, 0) = 0 for all x ∈ ℝⁿ lying in the closed ball of radius r centered at x₀ ∈ ℝⁿ, then u(x, t) = 0 for all (x, t) ∈ ℝⁿ × ℝ satisfying 0 ≤ t ≤ r and ||x − x₀|| ≤ r − t.</p>\n<p>The physical interpretation of this statement is that a disturbance in u at the point (x₁, t₁) can only affect u at (x₂, t₂) if t₂ − t₁ ≥ ||x₂ − x₁||, i.e., enough time has passed for the disturbance to travel from x₁ to x₂.</p>",
        "id": 543665787,
        "sender_full_name": "David K. Zhang",
        "timestamp": 1759903545
    },
    {
        "content": "<p>The usual proof of this statement, from Evans' textbook, is as follows:</p>\n<p><a href=\"/user_uploads/3121/eyKKbtioFRQlj7E9jHZqJj-T/Screenshot-2025-10-07-at-23.05.20.png\">Screenshot 2025-10-07 at 23.05.20.png</a></p>\n<div class=\"message_inline_image\"><a href=\"/user_uploads/3121/eyKKbtioFRQlj7E9jHZqJj-T/Screenshot-2025-10-07-at-23.05.20.png\" title=\"Screenshot 2025-10-07 at 23.05.20.png\"><img data-original-content-type=\"image/png\" data-original-dimensions=\"2012x1770\" src=\"/user_uploads/thumbnail/3121/eyKKbtioFRQlj7E9jHZqJj-T/Screenshot-2025-10-07-at-23.05.20.png/840x560.webp\"></a></div><p>You can see it requires a notion of multidimensional integration (Riemann is fine since we are only integrating continuous functions here) that supports multiple domains (ball and sphere), differentiation under the integral sign, and a multidimensional fundamental theorem of calculus (divergence theorem, i.e., Stokes' theorem for (n-1)-forms).</p>",
        "id": 543666200,
        "sender_full_name": "David K. Zhang",
        "timestamp": 1759903774
    },
    {
        "content": "<p>Is machinery of this type available in mathlib? I can see that there is a form of divergence theorem present (<a href=\"https://leanprover-community.github.io/mathlib4_docs/Mathlib/Analysis/BoxIntegral/DivergenceTheorem.html\">https://leanprover-community.github.io/mathlib4_docs/Mathlib/Analysis/BoxIntegral/DivergenceTheorem.html</a>) but it appears to only apply to box domains, with a nonstandard notion of integral?</p>\n<blockquote>\n<p>To make the proof work, we had to ban tagged partitions with “long and thin” boxes. More precisely, we use the following generalization of one-dimensional Henstock-Kurzweil integral to functions defined on a box in <code>ℝⁿ</code>...</p>\n</blockquote>",
        "id": 543667019,
        "sender_full_name": "David K. Zhang",
        "timestamp": 1759904268
    },
    {
        "content": "<p>In particular, it is not clear to me whether this notion of integral is compatible with the notion defined in <a href=\"https://leanprover-community.github.io/mathlib4_docs/Mathlib/Analysis/Calculus/ParametricIntegral.html\">https://leanprover-community.github.io/mathlib4_docs/Mathlib/Analysis/Calculus/ParametricIntegral.html</a> for differentiation under an integral sign. Can any Mathlib experts weigh in here?</p>",
        "id": 543667885,
        "sender_full_name": "David K. Zhang",
        "timestamp": 1759904764
    },
    {
        "content": "<p>Sadly we are missing a lot of things. We don't have the most general version of Stoke's theorem, but I know that some people is working on differential forms so hopefully we can have Stoke's theorem soon.</p>",
        "id": 543672152,
        "sender_full_name": "Yongxi Lin (Aaron)",
        "timestamp": 1759906809
    },
    {
        "content": "<p>The HK integral and the Bochner integral are also defined differently in mathlib and I don't think we have a theorem saying that these two are equivalent when we are working in <code>ℝⁿ</code>.</p>",
        "id": 543673213,
        "sender_full_name": "Yongxi Lin (Aaron)",
        "timestamp": 1759907183
    },
    {
        "content": "<p>There's no reason to use the HK integral though?</p>",
        "id": 543675836,
        "sender_full_name": "Heather Macbeth",
        "timestamp": 1759908210
    },
    {
        "content": "<p><span class=\"user-mention silent\" data-user-id=\"414458\">Vasily Ilin</span> <a href=\"#narrow/channel/534314-Lean-for-PDEs-2025/topic/Projects/near/543664599\">said</a>:</p>\n<blockquote>\n<p>Hi. I am trying to verify the solution to the heat equation -- project 1.</p>\n<div class=\"codehilite\" data-code-language=\"Lean4\"><pre><span></span><code><span class=\"kn\">import</span><span class=\"w\"> </span><span class=\"n\">Mathlib</span><span class=\"bp\">.</span><span class=\"n\">Probability</span><span class=\"bp\">.</span><span class=\"n\">Distributions</span><span class=\"bp\">.</span><span class=\"n\">Gaussian</span><span class=\"bp\">.</span><span class=\"n\">Real</span>\n<span class=\"kn\">open</span><span class=\"w\"> </span><span class=\"n\">ProbabilityTheory</span>\n\n<span class=\"kn\">noncomputable</span>\n<span class=\"kn\">def</span><span class=\"w\"> </span><span class=\"n\">f</span><span class=\"w\"> </span><span class=\"o\">(</span><span class=\"n\">t</span><span class=\"o\">:</span><span class=\"n\">ℝ</span><span class=\"o\">)</span><span class=\"w\"> </span><span class=\"n\">x</span><span class=\"w\"> </span><span class=\"o\">:=</span><span class=\"w\"> </span><span class=\"k\">if</span><span class=\"w\"> </span><span class=\"n\">ht</span><span class=\"w\"> </span><span class=\"o\">:</span><span class=\"w\"> </span><span class=\"mi\">0</span><span class=\"w\"> </span><span class=\"bp\">&lt;</span><span class=\"w\"> </span><span class=\"n\">t</span><span class=\"w\"> </span><span class=\"k\">then</span><span class=\"w\"> </span><span class=\"n\">gaussianPDFReal</span><span class=\"w\"> </span><span class=\"mi\">0</span><span class=\"w\"> </span><span class=\"bp\">⟨</span><span class=\"n\">t</span><span class=\"o\">,</span><span class=\"w\"> </span><span class=\"n\">le_of_lt</span><span class=\"w\"> </span><span class=\"n\">ht</span><span class=\"bp\">⟩</span><span class=\"w\"> </span><span class=\"n\">x</span><span class=\"w\"> </span><span class=\"k\">else</span><span class=\"w\"> </span><span class=\"mi\">0</span>\n\n<span class=\"kn\">lemma</span><span class=\"w\"> </span><span class=\"n\">deriv_t</span><span class=\"w\"> </span><span class=\"o\">{</span><span class=\"n\">x</span><span class=\"w\"> </span><span class=\"o\">:</span><span class=\"w\"> </span><span class=\"n\">ℝ</span><span class=\"o\">}</span><span class=\"w\"> </span><span class=\"o\">(</span><span class=\"n\">ht</span><span class=\"w\"> </span><span class=\"o\">:</span><span class=\"w\"> </span><span class=\"n\">t</span><span class=\"w\"> </span><span class=\"bp\">&gt;</span><span class=\"w\"> </span><span class=\"mi\">0</span><span class=\"o\">)</span><span class=\"w\"> </span><span class=\"o\">:</span><span class=\"w\"> </span><span class=\"n\">deriv</span><span class=\"w\"> </span><span class=\"o\">(</span><span class=\"k\">fun</span><span class=\"w\"> </span><span class=\"n\">t</span><span class=\"w\"> </span><span class=\"bp\">=&gt;</span><span class=\"w\"> </span><span class=\"n\">f</span><span class=\"w\"> </span><span class=\"n\">t</span><span class=\"w\"> </span><span class=\"n\">x</span><span class=\"o\">)</span><span class=\"w\"> </span><span class=\"n\">t</span><span class=\"w\"> </span><span class=\"bp\">=</span><span class=\"w\"> </span><span class=\"o\">(</span><span class=\"n\">f</span><span class=\"w\"> </span><span class=\"n\">t</span><span class=\"w\"> </span><span class=\"n\">x</span><span class=\"o\">)</span><span class=\"w\"> </span><span class=\"bp\">*</span><span class=\"w\"> </span><span class=\"o\">(</span><span class=\"bp\">-</span><span class=\"mi\">1</span><span class=\"bp\">/</span><span class=\"n\">t</span><span class=\"w\"> </span><span class=\"bp\">+</span><span class=\"w\"> </span><span class=\"n\">x</span><span class=\"bp\">^</span><span class=\"mi\">2</span><span class=\"bp\">/</span><span class=\"n\">t</span><span class=\"bp\">^</span><span class=\"mi\">2</span><span class=\"o\">)</span><span class=\"w\"> </span><span class=\"o\">:=</span><span class=\"w\"> </span><span class=\"k\">by</span>\n<span class=\"w\">  </span><span class=\"n\">unfold</span><span class=\"w\"> </span><span class=\"n\">f</span>\n<span class=\"w\">  </span><span class=\"n\">simp</span><span class=\"w\"> </span><span class=\"o\">[</span><span class=\"n\">ht</span><span class=\"o\">]</span><span class=\"w\"> </span><span class=\"c1\">-- does not simp under binder `deriv`</span>\n</code></pre></div>\n<p>I have two questions:</p>\n<ol>\n<li>Is this the right way to circumvent the fact that <code>deriv</code> expects a normed field but <code>gaussianPDFReal</code> takes a <code>NNReal</code>?</li>\n<li>How to simp <code>f</code> under the binder <code>deriv</code>?</li>\n</ol>\n</blockquote>\n<p>I think an easier way to define <code>f</code> is to use <code>toNNReal</code>, although I am not sure whether this can make it easier to prove your lemma.</p>\n<div class=\"codehilite\" data-code-language=\"Lean4\"><pre><span></span><code><span class=\"kn\">import</span><span class=\"w\"> </span><span class=\"n\">Mathlib</span><span class=\"bp\">.</span><span class=\"n\">Probability</span><span class=\"bp\">.</span><span class=\"n\">Distributions</span><span class=\"bp\">.</span><span class=\"n\">Gaussian</span><span class=\"bp\">.</span><span class=\"n\">Real</span>\n<span class=\"kn\">open</span><span class=\"w\"> </span><span class=\"n\">ProbabilityTheory</span><span class=\"w\"> </span><span class=\"n\">NNReal</span><span class=\"w\"> </span><span class=\"n\">Real</span>\n\n<span class=\"kn\">noncomputable</span>\n<span class=\"kn\">def</span><span class=\"w\"> </span><span class=\"n\">f</span><span class=\"w\"> </span><span class=\"o\">(</span><span class=\"n\">t</span><span class=\"o\">:</span><span class=\"n\">ℝ</span><span class=\"o\">)</span><span class=\"w\"> </span><span class=\"n\">x</span><span class=\"w\"> </span><span class=\"o\">:=</span><span class=\"w\"> </span><span class=\"n\">gaussianPDFReal</span><span class=\"w\"> </span><span class=\"mi\">0</span><span class=\"w\"> </span><span class=\"n\">t</span><span class=\"bp\">.</span><span class=\"n\">toNNReal</span><span class=\"w\"> </span><span class=\"n\">x</span>\n</code></pre></div>",
        "id": 543675955,
        "sender_full_name": "Yongxi Lin (Aaron)",
        "timestamp": 1759908263
    },
    {
        "content": "<p><span class=\"user-mention\" data-user-id=\"669043\">@Yongxi Lin</span> oof, that is <em>really</em> unfortunate. Without a developed theory of multivariate calculus in ℝⁿ we really cannot formalize much of PDE theory... We cannot even make it past the very first proof in Evans' PDE book (pg. 23) which uses all of these techniques (on a function with a singularity, no less).</p>",
        "id": 543676050,
        "sender_full_name": "David K. Zhang",
        "timestamp": 1759908302
    },
    {
        "content": "<p>One reason we don't have it now is that we want the most general result in mathlib and certainly we want Stoke's theorem for a general class of functions and a general class of domains (e.g. manifolds with boundary, potentially with some corners?). But the general version is hard to formalize.</p>",
        "id": 543683136,
        "sender_full_name": "Yongxi Lin (Aaron)",
        "timestamp": 1759910771
    },
    {
        "content": "<p>That makes sense, but in that case, it seems premature to hold a \"Lean for PDEs\" workshop when \"Lean for Calculus III\" is not yet a finished project. I suppose this is why, as <span class=\"user-mention\" data-user-id=\"110038\">@Kevin Buzzard</span> observes, most of the projects are merely of the form \"state something\" rather than \"prove something\"?</p>",
        "id": 543687303,
        "sender_full_name": "David K. Zhang",
        "timestamp": 1759912006
    },
    {
        "content": "<p>To be fair, I am not a PDE expert -- I am primarily a numerical analyst with only a few PDE courses under my belt. But it is my impression that energy arguments of this type (involving integration) are essential to get PDE theory off the ground.</p>",
        "id": 543688094,
        "sender_full_name": "David K. Zhang",
        "timestamp": 1759912215
    },
    {
        "content": "<p>For example, in proposed project <a href=\"https://github.com/leanprover-community/mathlib4/pull/1\">#1</a>:</p>\n<blockquote>\n<p>1) State the heat equation. Prove that that the standard convolution solution is a solution. Prove that this is the only solution.</p>\n</blockquote>\n<p>Both techniques I know to prove uniqueness of solutions for the heat equation, the energy method and the maximum principle, use integration in an essential way.</p>",
        "id": 543689363,
        "sender_full_name": "David K. Zhang",
        "timestamp": 1759912587
    },
    {
        "content": "<p>I would argue that some one-dimensional result for periodic heat/schrodinger equations are doable. We have results about <a href=\"https://leanprover-community.github.io/mathlib4_docs/Mathlib/Analysis/Fourier/AddCircleMulti.html\">Fourier series</a> and integration by part over an interval: <a href=\"https://leanprover-community.github.io/mathlib4_docs/Mathlib/MeasureTheory/Integral/IntervalIntegral/IntegrationByParts.html#intervalIntegral.integral_deriv_mul_eq_sub_of_hasDerivAt\">intervalIntegral.integral_deriv_mul_eq_sub_of_hasDerivAt</a>.</p>",
        "id": 543690049,
        "sender_full_name": "Yongxi Lin (Aaron)",
        "timestamp": 1759912795
    },
    {
        "content": "<p>Fair, but if (as you say) mathlib only wants theorems in general form, aren't such 1D restrictions throwaway practice projects with no hope of getting upstreamed into mathlib? The exploratory value also seems limited to me, since I doubt we will learn much about the necessary techniques to formalize the ND case from the 1D case.</p>",
        "id": 543691529,
        "sender_full_name": "David K. Zhang",
        "timestamp": 1759913205
    },
    {
        "content": "<p>Ah, I see the Fourier series results are indeed multivariate, so we might be able to do something for periodic functions over box domains. That seems potentially mathlib-worthy if we can synthetically work around multivariate integration, somehow...</p>",
        "id": 543692080,
        "sender_full_name": "David K. Zhang",
        "timestamp": 1759913374
    },
    {
        "content": "<p>Actually, I guess we could make progress by defining a purely formal \"multivariate integration operator\" that sends continuous functions on ℝⁿ to numbers in the right way (linearity, divergence theorem, preserves nonnegativity, etc.) and make all of our results conditional on the existence of such an operator, to leave an intentional gap that can be filled in when calculus on manifolds is sorted out at a later date (at least enough to get the results on ℝⁿ). Would that be an advisable way to proceed?</p>",
        "id": 543696042,
        "sender_full_name": "David K. Zhang",
        "timestamp": 1759914487
    },
    {
        "content": "<p><span class=\"user-mention silent\" data-user-id=\"974086\">David K. Zhang</span> <a href=\"#narrow/channel/534314-Lean-for-PDEs-2025/topic/Projects/near/543696042\">said</a>:</p>\n<blockquote>\n<p>Actually, I guess we could make progress by defining a purely formal \"multivariate integration operator\" that sends continuous functions on ℝⁿ to numbers in the right way</p>\n</blockquote>\n<p><span class=\"user-mention\" data-user-id=\"974086\">@David K. Zhang</span> This doesn't seem necessary to me: there's a full theory of the Bochner integral,  already well-used for multivariate integration, e.g <a href=\"https://arxiv.org/abs/2207.12742\">https://arxiv.org/abs/2207.12742</a>, <a href=\"https://drops.dagstuhl.de/entities/document/10.4230/LIPIcs.ITP.2024.37\">https://drops.dagstuhl.de/entities/document/10.4230/LIPIcs.ITP.2024.37</a>.</p>\n<p>The main gap I see for the early chapters of Evans is a version of Stokes' theorem for balls. It should be quite doable to state this using Hausdorff measure, and to prove it by a change of co-ordinates from the box version. I'd love to see someone work on this!  As you note, just the statement (black-boxed) would be good enough to go on with.</p>",
        "id": 543753808,
        "sender_full_name": "Heather Macbeth",
        "timestamp": 1759931575
    },
    {
        "content": "<p>And maybe also a version of spherical co-ordinates: a measure-preserving map between punctured space <span class=\"katex\"><span class=\"katex-mathml\"><math xmlns=\"http://www.w3.org/1998/Math/MathML\"><semantics><mrow><mi>V</mi><mo>∖</mo><mo stretchy=\"false\">{</mo><mn>0</mn><mo stretchy=\"false\">}</mo></mrow><annotation encoding=\"application/x-tex\">V\\setminus\\{0\\}</annotation></semantics></math></span><span class=\"katex-html\" aria-hidden=\"true\"><span class=\"base\"><span class=\"strut\" style=\"height:1em;vertical-align:-0.25em;\"></span><span class=\"mord mathnormal\" style=\"margin-right:0.22222em;\">V</span><span class=\"mspace\" style=\"margin-right:0.2222em;\"></span><span class=\"mbin\">∖</span><span class=\"mspace\" style=\"margin-right:0.2222em;\"></span></span><span class=\"base\"><span class=\"strut\" style=\"height:1em;vertical-align:-0.25em;\"></span><span class=\"mopen\">{</span><span class=\"mord\">0</span><span class=\"mclose\">}</span></span></span></span> and the cylinder <span class=\"katex\"><span class=\"katex-mathml\"><math xmlns=\"http://www.w3.org/1998/Math/MathML\"><semantics><mrow><msup><mi mathvariant=\"double-struck\">R</mi><mo>+</mo></msup><mo>×</mo><msub><mi>S</mi><mn>0</mn></msub><mo stretchy=\"false\">(</mo><mi>V</mi><mo stretchy=\"false\">)</mo></mrow><annotation encoding=\"application/x-tex\">\\mathbb{R}^+\\times S_0(V)</annotation></semantics></math></span><span class=\"katex-html\" aria-hidden=\"true\"><span class=\"base\"><span class=\"strut\" style=\"height:0.8547em;vertical-align:-0.0833em;\"></span><span class=\"mord\"><span class=\"mord mathbb\">R</span><span class=\"msupsub\"><span class=\"vlist-t\"><span class=\"vlist-r\"><span class=\"vlist\" style=\"height:0.7713em;\"><span style=\"top:-3.063em;margin-right:0.05em;\"><span class=\"pstrut\" style=\"height:2.7em;\"></span><span class=\"sizing reset-size6 size3 mtight\"><span class=\"mbin mtight\">+</span></span></span></span></span></span></span></span><span class=\"mspace\" style=\"margin-right:0.2222em;\"></span><span class=\"mbin\">×</span><span class=\"mspace\" style=\"margin-right:0.2222em;\"></span></span><span class=\"base\"><span class=\"strut\" style=\"height:1em;vertical-align:-0.25em;\"></span><span class=\"mord\"><span class=\"mord mathnormal\" style=\"margin-right:0.05764em;\">S</span><span class=\"msupsub\"><span class=\"vlist-t vlist-t2\"><span class=\"vlist-r\"><span class=\"vlist\" style=\"height:0.3011em;\"><span style=\"top:-2.55em;margin-left:-0.0576em;margin-right:0.05em;\"><span class=\"pstrut\" style=\"height:2.7em;\"></span><span class=\"sizing reset-size6 size3 mtight\"><span class=\"mord mtight\">0</span></span></span></span><span class=\"vlist-s\">​</span></span><span class=\"vlist-r\"><span class=\"vlist\" style=\"height:0.15em;\"><span></span></span></span></span></span></span><span class=\"mopen\">(</span><span class=\"mord mathnormal\" style=\"margin-right:0.22222em;\">V</span><span class=\"mclose\">)</span></span></span></span>, where the cylinder is equipped with the measure <span class=\"katex\"><span class=\"katex-mathml\"><math xmlns=\"http://www.w3.org/1998/Math/MathML\"><semantics><mrow><msup><mi>r</mi><mrow><mi>dim</mi><mo>⁡</mo><mi>V</mi><mo>−</mo><mn>1</mn></mrow></msup><msub><mi>μ</mi><mi mathvariant=\"double-struck\">R</mi></msub><mo>×</mo><msub><mi>μ</mi><mrow><msub><mi>S</mi><mn>0</mn></msub><mo stretchy=\"false\">(</mo><mi>V</mi><mo stretchy=\"false\">)</mo></mrow></msub></mrow><annotation encoding=\"application/x-tex\">r^{\\dim V-1}\\mu_\\mathbb{R}\\times \\mu_{S_0(V)}</annotation></semantics></math></span><span class=\"katex-html\" aria-hidden=\"true\"><span class=\"base\"><span class=\"strut\" style=\"height:1.0435em;vertical-align:-0.1944em;\"></span><span class=\"mord\"><span class=\"mord mathnormal\" style=\"margin-right:0.02778em;\">r</span><span class=\"msupsub\"><span class=\"vlist-t\"><span class=\"vlist-r\"><span class=\"vlist\" style=\"height:0.8491em;\"><span style=\"top:-3.063em;margin-right:0.05em;\"><span class=\"pstrut\" style=\"height:2.7em;\"></span><span class=\"sizing reset-size6 size3 mtight\"><span class=\"mord mtight\"><span class=\"mop mtight\"><span class=\"mtight\">d</span><span class=\"mtight\">i</span><span class=\"mtight\">m</span></span><span class=\"mspace mtight\" style=\"margin-right:0.1952em;\"></span><span class=\"mord mathnormal mtight\" style=\"margin-right:0.22222em;\">V</span><span class=\"mbin mtight\">−</span><span class=\"mord mtight\">1</span></span></span></span></span></span></span></span></span><span class=\"mord\"><span class=\"mord mathnormal\">μ</span><span class=\"msupsub\"><span class=\"vlist-t vlist-t2\"><span class=\"vlist-r\"><span class=\"vlist\" style=\"height:0.3322em;\"><span style=\"top:-2.55em;margin-left:0em;margin-right:0.05em;\"><span class=\"pstrut\" style=\"height:2.7em;\"></span><span class=\"sizing reset-size6 size3 mtight\"><span class=\"mord mathbb mtight\">R</span></span></span></span><span class=\"vlist-s\">​</span></span><span class=\"vlist-r\"><span class=\"vlist\" style=\"height:0.15em;\"><span></span></span></span></span></span></span><span class=\"mspace\" style=\"margin-right:0.2222em;\"></span><span class=\"mbin\">×</span><span class=\"mspace\" style=\"margin-right:0.2222em;\"></span></span><span class=\"base\"><span class=\"strut\" style=\"height:0.7858em;vertical-align:-0.3552em;\"></span><span class=\"mord\"><span class=\"mord mathnormal\">μ</span><span class=\"msupsub\"><span class=\"vlist-t vlist-t2\"><span class=\"vlist-r\"><span class=\"vlist\" style=\"height:0.3448em;\"><span style=\"top:-2.5198em;margin-left:0em;margin-right:0.05em;\"><span class=\"pstrut\" style=\"height:2.7em;\"></span><span class=\"sizing reset-size6 size3 mtight\"><span class=\"mord mtight\"><span class=\"mord mtight\"><span class=\"mord mathnormal mtight\" style=\"margin-right:0.05764em;\">S</span><span class=\"msupsub\"><span class=\"vlist-t vlist-t2\"><span class=\"vlist-r\"><span class=\"vlist\" style=\"height:0.3173em;\"><span style=\"top:-2.357em;margin-left:-0.0576em;margin-right:0.0714em;\"><span class=\"pstrut\" style=\"height:2.5em;\"></span><span class=\"sizing reset-size3 size1 mtight\"><span class=\"mord mtight\">0</span></span></span></span><span class=\"vlist-s\">​</span></span><span class=\"vlist-r\"><span class=\"vlist\" style=\"height:0.143em;\"><span></span></span></span></span></span></span><span class=\"mopen mtight\">(</span><span class=\"mord mathnormal mtight\" style=\"margin-right:0.22222em;\">V</span><span class=\"mclose mtight\">)</span></span></span></span></span><span class=\"vlist-s\">​</span></span><span class=\"vlist-r\"><span class=\"vlist\" style=\"height:0.3552em;\"><span></span></span></span></span></span></span></span></span></span> (where <span class=\"katex\"><span class=\"katex-mathml\"><math xmlns=\"http://www.w3.org/1998/Math/MathML\"><semantics><mrow><msub><mi>μ</mi><mrow><msub><mi>S</mi><mn>0</mn></msub><mo stretchy=\"false\">(</mo><mi>V</mi><mo stretchy=\"false\">)</mo></mrow></msub></mrow><annotation encoding=\"application/x-tex\">\\mu_{S_0(V)}</annotation></semantics></math></span><span class=\"katex-html\" aria-hidden=\"true\"><span class=\"base\"><span class=\"strut\" style=\"height:0.7858em;vertical-align:-0.3552em;\"></span><span class=\"mord\"><span class=\"mord mathnormal\">μ</span><span class=\"msupsub\"><span class=\"vlist-t vlist-t2\"><span class=\"vlist-r\"><span class=\"vlist\" style=\"height:0.3448em;\"><span style=\"top:-2.5198em;margin-left:0em;margin-right:0.05em;\"><span class=\"pstrut\" style=\"height:2.7em;\"></span><span class=\"sizing reset-size6 size3 mtight\"><span class=\"mord mtight\"><span class=\"mord mtight\"><span class=\"mord mathnormal mtight\" style=\"margin-right:0.05764em;\">S</span><span class=\"msupsub\"><span class=\"vlist-t vlist-t2\"><span class=\"vlist-r\"><span class=\"vlist\" style=\"height:0.3173em;\"><span style=\"top:-2.357em;margin-left:-0.0576em;margin-right:0.0714em;\"><span class=\"pstrut\" style=\"height:2.5em;\"></span><span class=\"sizing reset-size3 size1 mtight\"><span class=\"mord mtight\">0</span></span></span></span><span class=\"vlist-s\">​</span></span><span class=\"vlist-r\"><span class=\"vlist\" style=\"height:0.143em;\"><span></span></span></span></span></span></span><span class=\"mopen mtight\">(</span><span class=\"mord mathnormal mtight\" style=\"margin-right:0.22222em;\">V</span><span class=\"mclose mtight\">)</span></span></span></span></span><span class=\"vlist-s\">​</span></span><span class=\"vlist-r\"><span class=\"vlist\" style=\"height:0.3552em;\"><span></span></span></span></span></span></span></span></span></span> denotes Hausdorff measure).</p>",
        "id": 543761803,
        "sender_full_name": "Heather Macbeth",
        "timestamp": 1759933448
    },
    {
        "content": "<p><span class=\"user-mention\" data-user-id=\"414458\">@Vasily Ilin</span> For your \"simp under binders\" question, the issue is actually slightly different. You have two functions (let's call them <code>f</code> and <code>g</code>), which are equal near <code>t</code> --- and you need to show that <code>deriv f t = deriv g t</code>. This does not only depend on the value at <code>t</code>, but on <code>f</code> and <code>t</code> in a neighbourhood of <code>t</code>. So, you need to apply a suitable lemma.</p>",
        "id": 543787374,
        "sender_full_name": "Michael Rothgang",
        "timestamp": 1759940105
    },
    {
        "content": "<p>If you hear \"binder\", really think of a forall or exists quantifier.</p>",
        "id": 543787554,
        "sender_full_name": "Michael Rothgang",
        "timestamp": 1759940167
    },
    {
        "content": "<p>Here's a start on how to do such a rewriting:</p>\n<div class=\"codehilite\" data-code-language=\"Lean4\"><pre><span></span><code><span class=\"kn\">import</span><span class=\"w\"> </span><span class=\"n\">Mathlib</span>\n\n<span class=\"kn\">open</span><span class=\"w\"> </span><span class=\"n\">ProbabilityTheory</span>\n\n<span class=\"kn\">noncomputable</span>\n<span class=\"kn\">def</span><span class=\"w\"> </span><span class=\"n\">f</span><span class=\"w\"> </span><span class=\"o\">(</span><span class=\"n\">t</span><span class=\"w\"> </span><span class=\"o\">:</span><span class=\"w\"> </span><span class=\"n\">ℝ</span><span class=\"o\">)</span><span class=\"w\"> </span><span class=\"n\">x</span><span class=\"w\"> </span><span class=\"o\">:=</span><span class=\"w\"> </span><span class=\"n\">gaussianPDFReal</span><span class=\"w\"> </span><span class=\"mi\">0</span><span class=\"w\"> </span><span class=\"n\">t</span><span class=\"bp\">.</span><span class=\"n\">toNNReal</span><span class=\"w\"> </span><span class=\"n\">x</span>\n\n<span class=\"kn\">lemma</span><span class=\"w\"> </span><span class=\"n\">deriv_t</span><span class=\"w\"> </span><span class=\"o\">{</span><span class=\"n\">t</span><span class=\"w\"> </span><span class=\"n\">x</span><span class=\"w\"> </span><span class=\"o\">:</span><span class=\"w\"> </span><span class=\"n\">ℝ</span><span class=\"o\">}</span><span class=\"w\"> </span><span class=\"o\">(</span><span class=\"n\">ht</span><span class=\"w\"> </span><span class=\"o\">:</span><span class=\"w\"> </span><span class=\"n\">t</span><span class=\"w\"> </span><span class=\"bp\">&gt;</span><span class=\"w\"> </span><span class=\"mi\">0</span><span class=\"o\">)</span><span class=\"w\"> </span><span class=\"o\">:</span><span class=\"w\"> </span><span class=\"n\">deriv</span><span class=\"w\"> </span><span class=\"o\">(</span><span class=\"k\">fun</span><span class=\"w\"> </span><span class=\"n\">t</span><span class=\"w\"> </span><span class=\"bp\">↦</span><span class=\"w\"> </span><span class=\"n\">f</span><span class=\"w\"> </span><span class=\"n\">t</span><span class=\"w\"> </span><span class=\"n\">x</span><span class=\"o\">)</span><span class=\"w\"> </span><span class=\"n\">t</span><span class=\"w\"> </span><span class=\"bp\">=</span><span class=\"w\"> </span><span class=\"o\">(</span><span class=\"n\">f</span><span class=\"w\"> </span><span class=\"n\">t</span><span class=\"w\"> </span><span class=\"n\">x</span><span class=\"o\">)</span><span class=\"w\"> </span><span class=\"bp\">*</span><span class=\"w\"> </span><span class=\"o\">(</span><span class=\"bp\">-</span><span class=\"mi\">1</span><span class=\"w\"> </span><span class=\"bp\">/</span><span class=\"w\"> </span><span class=\"n\">t</span><span class=\"w\"> </span><span class=\"bp\">+</span><span class=\"w\"> </span><span class=\"n\">x</span><span class=\"bp\">^</span><span class=\"mi\">2</span><span class=\"w\"> </span><span class=\"bp\">/</span><span class=\"w\"> </span><span class=\"n\">t</span><span class=\"bp\">^</span><span class=\"mi\">2</span><span class=\"o\">)</span><span class=\"w\"> </span><span class=\"o\">:=</span><span class=\"w\"> </span><span class=\"k\">by</span>\n<span class=\"w\">  </span><span class=\"n\">unfold</span><span class=\"w\"> </span><span class=\"n\">f</span><span class=\"w\"> </span><span class=\"n\">gaussianPDFReal</span>\n<span class=\"w\">  </span><span class=\"n\">simp</span>\n<span class=\"w\">  </span><span class=\"c1\">-- Idea: because t is positive, near `t` each `max t 0` is actually `t`, and we want to</span>\n<span class=\"w\">  </span><span class=\"c1\">-- differentiate a simpler expression.</span>\n<span class=\"w\">  </span><span class=\"c1\">-- This is the function we're differentiating now.</span>\n<span class=\"w\">  </span><span class=\"n\">set</span><span class=\"w\"> </span><span class=\"n\">g1</span><span class=\"w\"> </span><span class=\"o\">:=</span><span class=\"w\"> </span><span class=\"k\">fun</span><span class=\"w\"> </span><span class=\"n\">t</span><span class=\"w\"> </span><span class=\"bp\">↦</span><span class=\"w\"> </span><span class=\"o\">(</span><span class=\"bp\">√</span><span class=\"o\">(</span><span class=\"n\">max</span><span class=\"w\"> </span><span class=\"n\">t</span><span class=\"w\"> </span><span class=\"mi\">0</span><span class=\"o\">))</span><span class=\"bp\">⁻¹</span><span class=\"w\"> </span><span class=\"bp\">*</span><span class=\"w\"> </span><span class=\"o\">((</span><span class=\"bp\">√</span><span class=\"n\">Real</span><span class=\"bp\">.</span><span class=\"n\">pi</span><span class=\"o\">)</span><span class=\"bp\">⁻¹</span><span class=\"w\"> </span><span class=\"bp\">*</span><span class=\"w\"> </span><span class=\"o\">(</span><span class=\"bp\">√</span><span class=\"mi\">2</span><span class=\"o\">)</span><span class=\"bp\">⁻¹</span><span class=\"o\">)</span><span class=\"w\"> </span><span class=\"bp\">*</span><span class=\"w\"> </span><span class=\"n\">Real</span><span class=\"bp\">.</span><span class=\"n\">exp</span><span class=\"w\"> </span><span class=\"o\">(</span><span class=\"bp\">-</span><span class=\"n\">x</span><span class=\"w\"> </span><span class=\"bp\">^</span><span class=\"w\"> </span><span class=\"mi\">2</span><span class=\"w\"> </span><span class=\"bp\">/</span><span class=\"w\"> </span><span class=\"o\">(</span><span class=\"mi\">2</span><span class=\"w\"> </span><span class=\"bp\">*</span><span class=\"w\"> </span><span class=\"n\">max</span><span class=\"w\"> </span><span class=\"n\">t</span><span class=\"w\"> </span><span class=\"mi\">0</span><span class=\"o\">))</span>\n<span class=\"w\">  </span><span class=\"c1\">-- This is the function we want to differentiate.</span>\n<span class=\"w\">  </span><span class=\"k\">let</span><span class=\"w\"> </span><span class=\"n\">g</span><span class=\"w\"> </span><span class=\"o\">:=</span><span class=\"w\"> </span><span class=\"k\">fun</span><span class=\"w\"> </span><span class=\"n\">t</span><span class=\"w\"> </span><span class=\"bp\">↦</span><span class=\"w\"> </span><span class=\"o\">(</span><span class=\"bp\">√</span><span class=\"n\">t</span><span class=\"o\">)</span><span class=\"bp\">⁻¹</span><span class=\"w\"> </span><span class=\"bp\">*</span><span class=\"w\"> </span><span class=\"o\">((</span><span class=\"bp\">√</span><span class=\"n\">Real</span><span class=\"bp\">.</span><span class=\"n\">pi</span><span class=\"o\">)</span><span class=\"bp\">⁻¹</span><span class=\"w\"> </span><span class=\"bp\">*</span><span class=\"w\"> </span><span class=\"o\">(</span><span class=\"bp\">√</span><span class=\"mi\">2</span><span class=\"o\">)</span><span class=\"bp\">⁻¹</span><span class=\"o\">)</span><span class=\"w\"> </span><span class=\"bp\">*</span><span class=\"w\"> </span><span class=\"n\">Real</span><span class=\"bp\">.</span><span class=\"n\">exp</span><span class=\"w\"> </span><span class=\"o\">(</span><span class=\"bp\">-</span><span class=\"n\">x</span><span class=\"w\"> </span><span class=\"bp\">^</span><span class=\"w\"> </span><span class=\"mi\">2</span><span class=\"w\"> </span><span class=\"bp\">/</span><span class=\"w\"> </span><span class=\"o\">(</span><span class=\"mi\">2</span><span class=\"w\"> </span><span class=\"bp\">*</span><span class=\"w\"> </span><span class=\"n\">t</span><span class=\"o\">))</span>\n<span class=\"w\">  </span><span class=\"k\">have</span><span class=\"w\"> </span><span class=\"n\">hg</span><span class=\"w\"> </span><span class=\"o\">(</span><span class=\"n\">t</span><span class=\"o\">)</span><span class=\"w\"> </span><span class=\"o\">(</span><span class=\"n\">ht</span><span class=\"w\"> </span><span class=\"o\">:</span><span class=\"w\"> </span><span class=\"mi\">0</span><span class=\"w\"> </span><span class=\"bp\">&lt;</span><span class=\"w\"> </span><span class=\"n\">t</span><span class=\"o\">)</span><span class=\"w\"> </span><span class=\"o\">:</span><span class=\"w\"> </span><span class=\"n\">g1</span><span class=\"w\"> </span><span class=\"n\">t</span><span class=\"w\"> </span><span class=\"bp\">=</span><span class=\"w\"> </span><span class=\"n\">g</span><span class=\"w\"> </span><span class=\"n\">t</span><span class=\"w\"> </span><span class=\"o\">:=</span><span class=\"w\"> </span><span class=\"k\">by</span>\n<span class=\"w\">    </span><span class=\"gr\">sorry</span><span class=\"w\"> </span><span class=\"c1\">-- exercise: prove this</span>\n<span class=\"w\">  </span><span class=\"k\">have</span><span class=\"w\"> </span><span class=\"n\">hg'</span><span class=\"w\"> </span><span class=\"o\">:</span><span class=\"w\"> </span><span class=\"n\">g1</span><span class=\"w\"> </span><span class=\"bp\">=ᶠ</span><span class=\"o\">[</span><span class=\"n\">nhds</span><span class=\"w\"> </span><span class=\"n\">t</span><span class=\"o\">]</span><span class=\"w\"> </span><span class=\"n\">g</span><span class=\"w\"> </span><span class=\"o\">:=</span><span class=\"w\"> </span><span class=\"k\">by</span>\n<span class=\"w\">    </span><span class=\"gr\">sorry</span><span class=\"w\"> </span><span class=\"c1\">-- this is `hg` stated differently</span>\n<span class=\"w\">  </span><span class=\"n\">rw</span><span class=\"w\"> </span><span class=\"o\">[</span><span class=\"n\">Filter</span><span class=\"bp\">.</span><span class=\"n\">EventuallyEq</span><span class=\"bp\">.</span><span class=\"n\">deriv_eq</span><span class=\"w\"> </span><span class=\"n\">hg'</span><span class=\"o\">]</span>\n<span class=\"w\">  </span><span class=\"gr\">sorry</span>\n</code></pre></div>",
        "id": 543788276,
        "sender_full_name": "Michael Rothgang",
        "timestamp": 1759940390
    },
    {
        "content": "<p>Let me second what Heather says about Stokes' theorem: if you can state the version you want to use, you're allowed to black-box it and move on!</p>",
        "id": 543788843,
        "sender_full_name": "Michael Rothgang",
        "timestamp": 1759940584
    },
    {
        "content": "<p>(Differential forms are coming to mathlib, and we want Stokes's theorem for sure, e.g. deduced on manifolds with corners. But this will take in the order of a few months.)</p>",
        "id": 543788951,
        "sender_full_name": "Michael Rothgang",
        "timestamp": 1759940619
    },
    {
        "content": "<p>Hi all, I am playing around with some differential equations from physics. I am currently trying to formalize a lemma where I am effectively taking a limit of a function to show that it tends to a particular function in the certain limit. Say we have k sinh(r/k). How would I go about showing  k sinh(r/k) tends to r in the limit of k to infty? I am trying to search for a limit documentation in Mathlib, but I can't really find a reference. Thanks!</p>",
        "id": 544063257,
        "sender_full_name": "Luis Gabriel Bariuan",
        "timestamp": 1760054159
    },
    {
        "content": "<p>The keyword for limits is <code>Tendsto</code>, as in <a href=\"https://leanprover-community.github.io/mathlib4_docs/Mathlib/Order/Filter/Defs.html#Filter.Tendsto\">Filter.Tendsto</a><br>\nI recommend reading the <a href=\"https://leanprover-community.github.io/mathematics_in_lean/C11_Topology.html\">topology chapter of Mathematics in Lean</a> to learn about that.</p>",
        "id": 544063481,
        "sender_full_name": "Rémy Degenne",
        "timestamp": 1760054346
    },
    {
        "content": "<p>This is how you write that a function tends to a limit at infinity:</p>\n<div class=\"codehilite\" data-code-language=\"Lean4\"><pre><span></span><code><span class=\"kn\">import</span><span class=\"w\"> </span><span class=\"n\">Mathlib</span>\n<span class=\"kn\">open</span><span class=\"w\"> </span><span class=\"n\">Filter</span>\n<span class=\"kn\">open</span><span class=\"w\"> </span><span class=\"kn\">scoped</span><span class=\"w\"> </span><span class=\"n\">Topology</span>\n\n<span class=\"kn\">example</span><span class=\"w\"> </span><span class=\"o\">{</span><span class=\"n\">f</span><span class=\"w\"> </span><span class=\"o\">:</span><span class=\"w\"> </span><span class=\"n\">ℝ</span><span class=\"w\"> </span><span class=\"bp\">→</span><span class=\"w\"> </span><span class=\"n\">ℝ</span><span class=\"o\">}</span><span class=\"w\"> </span><span class=\"o\">{</span><span class=\"n\">l</span><span class=\"w\"> </span><span class=\"o\">:</span><span class=\"w\"> </span><span class=\"n\">ℝ</span><span class=\"o\">}</span><span class=\"w\"> </span><span class=\"o\">:</span><span class=\"w\"> </span><span class=\"n\">Tendsto</span><span class=\"w\"> </span><span class=\"n\">f</span><span class=\"w\"> </span><span class=\"n\">atTop</span><span class=\"w\"> </span><span class=\"o\">(</span><span class=\"n\">𝓝</span><span class=\"w\"> </span><span class=\"n\">l</span><span class=\"o\">)</span><span class=\"w\"> </span><span class=\"o\">:=</span><span class=\"w\"> </span><span class=\"gr\">sorry</span>\n</code></pre></div>",
        "id": 544063611,
        "sender_full_name": "Rémy Degenne",
        "timestamp": 1760054437
    },
    {
        "content": "<p>The \"at infinity\" part is given by the <a href=\"https://leanprover-community.github.io/mathlib4_docs/Mathlib/Order/Filter/AtTopBot/Defs.html#Filter.atTop\">Filter.atTop</a> filter.</p>",
        "id": 544063657,
        "sender_full_name": "Rémy Degenne",
        "timestamp": 1760054465
    },
    {
        "content": "<p>Not knowing what has transpired at the workshop, nor an expert in PDEs (or Lean for that matter), I think the decision for formalizing PDEs would be torn by what generalizations we would want to eventually cover. The linear PDEs has a general theory (cf Hormander's treatise), heavily relying on the theory of distributions, while the nonlinear ones do not usually employ distributions (multiplication being undefined) but emphasize estimates/inequalities of various sorts (Evans' book seems to be of the latter kind). The wave equation is at the crossroad here, more so perhaps than the heat and Laplace's equations: the finite speed of propogation, for example, would be a statement of the support of the fundamental solution, and before that one would need existence and uniqueness. Given the style of abstraction in the rest of mathlib, it seems that distributions would be a natural object to formalize first.</p>",
        "id": 545906144,
        "sender_full_name": "Yao Liu",
        "timestamp": 1760947760
    },
    {
        "content": "<p>Distributions are being actively worked on right now: Moritz Doll is working on tempered distributions (and a number of these changes are open pull requests right now, waiting for review); Anatole Dedecker and Luigi Massacci have formalised distributions (and basic facts, such as a locally integrable function inducing a distribution). That work is also currently under review.</p>",
        "id": 545908217,
        "sender_full_name": "Michael Rothgang",
        "timestamp": 1760948365
    },
    {
        "content": "<p>Filippo Nuccio and I are formalising Sobolev spaces on top of Anatole and Luigi's work.</p>",
        "id": 545908317,
        "sender_full_name": "Michael Rothgang",
        "timestamp": 1760948389
    },
    {
        "content": "<p>That's wonderful. I'll take a look, and if I can find the time I may (finally) contribute something. One thing that I recall that I needed (for my work) was that the distributions supported at a point must be of the form of the delta function and (finitely many of) its derivatives. Do you have that already?</p>\n<p>Out of curiosity, is the spectral theory (say the spectrum is discrete for the Laplacian on a compact domain) something that could come out of this push on PDE? One approach seems to involve the Sobolev space.</p>",
        "id": 545935992,
        "sender_full_name": "Yao Liu",
        "timestamp": 1760955996
    },
    {
        "content": "<p>I'm not sure if that's somewhere, waiting for review. <span class=\"user-mention\" data-user-id=\"466290\">@Luigi Massacci</span> Do you have this? If not, is there a good branch of course that includes your work so far, that one could work on top of?</p>",
        "id": 545957020,
        "sender_full_name": "Michael Rothgang",
        "timestamp": 1760961814
    },
    {
        "content": "<p>I haven't thought about spectral theory so far (nor checked how much of it is in mathlib). If indeed missing, this would certainly be a worthwhile yet.</p>",
        "id": 545957043,
        "sender_full_name": "Michael Rothgang",
        "timestamp": 1760961822
    },
    {
        "content": "<p>Let me mention this post over here <a class=\"stream-topic\" data-stream-id=\"287929\" href=\"/#narrow/channel/287929-mathlib4/topic/Tychonov.27s.20Counterexample.20for.20the.20Heat.20Equation/with/547234576\">#mathlib4 &gt; Tychonov's Counterexample for the Heat Equation</a>  as I think some PDE people may be interested in this.</p>",
        "id": 547235302,
        "sender_full_name": "Yongxi Lin (Aaron)",
        "timestamp": 1761559414
    }
]