[
    {
        "content": "<div class=\"codehilite\" data-code-language=\"Lean4\"><pre><span></span><code><span class=\"kn\">import</span><span class=\"w\"> </span><span class=\"n\">Mathlib</span>\n<span class=\"kn\">theorem</span><span class=\"w\"> </span><span class=\"n\">foo</span><span class=\"w\"> </span><span class=\"o\">{</span><span class=\"n\">α</span><span class=\"w\"> </span><span class=\"n\">β</span><span class=\"w\"> </span><span class=\"o\">:</span><span class=\"w\"> </span><span class=\"kt\">Type</span><span class=\"bp\">*</span><span class=\"o\">}</span><span class=\"w\"> </span><span class=\"o\">{</span><span class=\"n\">l₁</span><span class=\"w\"> </span><span class=\"n\">l₂</span><span class=\"w\"> </span><span class=\"o\">:</span><span class=\"w\"> </span><span class=\"n\">List</span><span class=\"w\"> </span><span class=\"o\">(</span><span class=\"n\">α</span><span class=\"w\"> </span><span class=\"bp\">×</span><span class=\"w\"> </span><span class=\"n\">β</span><span class=\"o\">)}</span>\n<span class=\"w\">    </span><span class=\"o\">(</span><span class=\"n\">h₁</span><span class=\"w\"> </span><span class=\"o\">:</span><span class=\"w\"> </span><span class=\"n\">l₁</span><span class=\"bp\">.</span><span class=\"n\">map</span><span class=\"w\"> </span><span class=\"n\">Prod</span><span class=\"bp\">.</span><span class=\"n\">fst</span><span class=\"w\"> </span><span class=\"bp\">=</span><span class=\"w\"> </span><span class=\"n\">l₂</span><span class=\"bp\">.</span><span class=\"n\">map</span><span class=\"w\"> </span><span class=\"n\">Prod</span><span class=\"bp\">.</span><span class=\"n\">fst</span><span class=\"o\">)</span>\n<span class=\"w\">    </span><span class=\"o\">(</span><span class=\"n\">h₂</span><span class=\"w\"> </span><span class=\"o\">:</span><span class=\"w\"> </span><span class=\"n\">l₁</span><span class=\"bp\">.</span><span class=\"n\">map</span><span class=\"w\"> </span><span class=\"n\">Prod</span><span class=\"bp\">.</span><span class=\"n\">snd</span><span class=\"w\"> </span><span class=\"bp\">=</span><span class=\"w\"> </span><span class=\"n\">l₂</span><span class=\"bp\">.</span><span class=\"n\">map</span><span class=\"w\"> </span><span class=\"n\">Prod</span><span class=\"bp\">.</span><span class=\"n\">snd</span><span class=\"o\">)</span><span class=\"w\"> </span><span class=\"o\">:</span><span class=\"w\"> </span><span class=\"n\">l₁</span><span class=\"w\"> </span><span class=\"bp\">=</span><span class=\"w\"> </span><span class=\"n\">l₂</span><span class=\"w\"> </span><span class=\"o\">:=</span><span class=\"w\"> </span><span class=\"k\">by</span>\n<span class=\"w\">  </span><span class=\"gr\">sorry</span>\n</code></pre></div>\n<p>I think the strategy would be to first get <code>l₁.map f = l₂.map f</code> where <code>f = fun p ↦ Prod.mk (Prod.fst p) (Prod.snd p)</code> and then claim <code>f = id</code>.<br>\nThis \"combining 2 maps\" thing surely already exists, but I couldn't find it.</p>",
        "id": 560187460,
        "sender_full_name": "Snir Broshi",
        "timestamp": 1764084950
    },
    {
        "content": "<p>How about this:</p>\n<div class=\"codehilite\" data-code-language=\"Lean4\"><pre><span></span><code><span class=\"kn\">import</span><span class=\"w\"> </span><span class=\"n\">Mathlib</span>\n\n<span class=\"kn\">theorem</span><span class=\"w\"> </span><span class=\"n\">List</span><span class=\"bp\">.</span><span class=\"n\">unzip_inj</span><span class=\"w\"> </span><span class=\"o\">{</span><span class=\"n\">α</span><span class=\"w\"> </span><span class=\"n\">β</span><span class=\"w\"> </span><span class=\"o\">:</span><span class=\"w\"> </span><span class=\"kt\">Type</span><span class=\"bp\">*</span><span class=\"o\">}</span><span class=\"w\"> </span><span class=\"o\">{</span><span class=\"n\">l₁</span><span class=\"w\"> </span><span class=\"n\">l₂</span><span class=\"w\"> </span><span class=\"o\">:</span><span class=\"w\"> </span><span class=\"n\">List</span><span class=\"w\"> </span><span class=\"o\">(</span><span class=\"n\">α</span><span class=\"w\"> </span><span class=\"bp\">×</span><span class=\"w\"> </span><span class=\"n\">β</span><span class=\"o\">)}</span><span class=\"w\"> </span><span class=\"o\">:</span>\n<span class=\"w\">    </span><span class=\"n\">l₁</span><span class=\"bp\">.</span><span class=\"n\">unzip</span><span class=\"w\"> </span><span class=\"bp\">=</span><span class=\"w\"> </span><span class=\"n\">l₂</span><span class=\"bp\">.</span><span class=\"n\">unzip</span><span class=\"w\"> </span><span class=\"bp\">↔</span><span class=\"w\"> </span><span class=\"n\">l₁</span><span class=\"w\"> </span><span class=\"bp\">=</span><span class=\"w\"> </span><span class=\"n\">l₂</span><span class=\"w\"> </span><span class=\"o\">:=</span><span class=\"w\"> </span><span class=\"k\">by</span>\n<span class=\"w\">  </span><span class=\"n\">refine</span><span class=\"w\"> </span><span class=\"bp\">⟨</span><span class=\"k\">fun</span><span class=\"w\"> </span><span class=\"n\">h</span><span class=\"w\"> </span><span class=\"bp\">=&gt;</span><span class=\"w\"> </span><span class=\"bp\">?_</span><span class=\"o\">,</span><span class=\"w\"> </span><span class=\"k\">fun</span><span class=\"w\"> </span><span class=\"n\">h</span><span class=\"w\"> </span><span class=\"bp\">=&gt;</span><span class=\"w\"> </span><span class=\"n\">h</span><span class=\"w\"> </span><span class=\"bp\">▸</span><span class=\"w\"> </span><span class=\"n\">rfl</span><span class=\"bp\">⟩</span>\n<span class=\"w\">  </span><span class=\"n\">rw</span><span class=\"w\"> </span><span class=\"o\">[</span><span class=\"bp\">←</span><span class=\"w\"> </span><span class=\"n\">zip_unzip</span><span class=\"w\"> </span><span class=\"n\">l₁</span><span class=\"o\">,</span><span class=\"w\"> </span><span class=\"bp\">←</span><span class=\"w\"> </span><span class=\"n\">zip_unzip</span><span class=\"w\"> </span><span class=\"n\">l₂</span><span class=\"o\">,</span><span class=\"w\"> </span><span class=\"n\">h</span><span class=\"o\">]</span>\n\n<span class=\"kn\">theorem</span><span class=\"w\"> </span><span class=\"n\">foo</span><span class=\"w\"> </span><span class=\"o\">{</span><span class=\"n\">α</span><span class=\"w\"> </span><span class=\"n\">β</span><span class=\"w\"> </span><span class=\"o\">:</span><span class=\"w\"> </span><span class=\"kt\">Type</span><span class=\"bp\">*</span><span class=\"o\">}</span><span class=\"w\"> </span><span class=\"o\">{</span><span class=\"n\">l₁</span><span class=\"w\"> </span><span class=\"n\">l₂</span><span class=\"w\"> </span><span class=\"o\">:</span><span class=\"w\"> </span><span class=\"n\">List</span><span class=\"w\"> </span><span class=\"o\">(</span><span class=\"n\">α</span><span class=\"w\"> </span><span class=\"bp\">×</span><span class=\"w\"> </span><span class=\"n\">β</span><span class=\"o\">)}</span>\n<span class=\"w\">    </span><span class=\"o\">(</span><span class=\"n\">h₁</span><span class=\"w\"> </span><span class=\"o\">:</span><span class=\"w\"> </span><span class=\"n\">l₁</span><span class=\"bp\">.</span><span class=\"n\">map</span><span class=\"w\"> </span><span class=\"n\">Prod</span><span class=\"bp\">.</span><span class=\"n\">fst</span><span class=\"w\"> </span><span class=\"bp\">=</span><span class=\"w\"> </span><span class=\"n\">l₂</span><span class=\"bp\">.</span><span class=\"n\">map</span><span class=\"w\"> </span><span class=\"n\">Prod</span><span class=\"bp\">.</span><span class=\"n\">fst</span><span class=\"o\">)</span>\n<span class=\"w\">    </span><span class=\"o\">(</span><span class=\"n\">h₂</span><span class=\"w\"> </span><span class=\"o\">:</span><span class=\"w\"> </span><span class=\"n\">l₁</span><span class=\"bp\">.</span><span class=\"n\">map</span><span class=\"w\"> </span><span class=\"n\">Prod</span><span class=\"bp\">.</span><span class=\"n\">snd</span><span class=\"w\"> </span><span class=\"bp\">=</span><span class=\"w\"> </span><span class=\"n\">l₂</span><span class=\"bp\">.</span><span class=\"n\">map</span><span class=\"w\"> </span><span class=\"n\">Prod</span><span class=\"bp\">.</span><span class=\"n\">snd</span><span class=\"o\">)</span><span class=\"w\"> </span><span class=\"o\">:</span><span class=\"w\"> </span><span class=\"n\">l₁</span><span class=\"w\"> </span><span class=\"bp\">=</span><span class=\"w\"> </span><span class=\"n\">l₂</span><span class=\"w\"> </span><span class=\"o\">:=</span><span class=\"w\"> </span><span class=\"k\">by</span>\n<span class=\"w\">  </span><span class=\"n\">rw</span><span class=\"w\"> </span><span class=\"o\">[</span><span class=\"bp\">←</span><span class=\"w\"> </span><span class=\"n\">List</span><span class=\"bp\">.</span><span class=\"n\">unzip_inj</span><span class=\"o\">,</span><span class=\"w\"> </span><span class=\"n\">List</span><span class=\"bp\">.</span><span class=\"n\">unzip_eq_map</span><span class=\"o\">,</span><span class=\"w\"> </span><span class=\"n\">List</span><span class=\"bp\">.</span><span class=\"n\">unzip_eq_map</span><span class=\"o\">,</span><span class=\"w\"> </span><span class=\"n\">h₁</span><span class=\"o\">,</span><span class=\"w\"> </span><span class=\"n\">h₂</span><span class=\"o\">]</span>\n</code></pre></div>",
        "id": 560192334,
        "sender_full_name": "Markus Himmel",
        "timestamp": 1764086127
    },
    {
        "content": "<p>Cool, thanks!<br>\n<del><code>List.unzip</code> is useful in this case, but is there a general function to combine two lists with <code>map</code>?</del><br>\n<del>Found it: <a href=\"https://leanprover-community.github.io/mathlib4_docs/find/?pattern=List.map%E2%82%82Left#doc\">docs#List.map₂Left</a> and <a href=\"https://leanprover-community.github.io/mathlib4_docs/find/?pattern=List.map%E2%82%82Right#doc\">docs#List.map₂Right</a>. I wonder if they can help here, though they seem to have very little API</del><br>\n<a href=\"https://leanprover-community.github.io/mathlib4_docs/find/?pattern=List.zipWith#doc\">docs#List.zipWith</a> is probably the general way to combine two maps</p>",
        "id": 560195431,
        "sender_full_name": "Snir Broshi",
        "timestamp": 1764086869
    },
    {
        "content": "<p>Some version of this is now <a href=\"https://github.com/leanprover-community/mathlib4/pull/32106\">#32106</a></p>",
        "id": 560202529,
        "sender_full_name": "Snir Broshi",
        "timestamp": 1764088758
    }
]