[
    {
        "content": "<p>I have a probability distribution over <code>A → A</code> and I would like to get a probability distribution for its composition with itself (I compose a random operation with another random operation — what is the probability for the resulting operation?).</p>",
        "id": 411729116,
        "sender_full_name": "Martin Dvořák",
        "timestamp": 1704716963
    },
    {
        "content": "<p>That sounds like a good use for the putative <code>Measure.map₂</code>, <span class=\"user-mention\" data-user-id=\"214703\">@Yury G. Kudryashov</span></p>",
        "id": 411729376,
        "sender_full_name": "Yaël Dillies",
        "timestamp": 1704717053
    },
    {
        "content": "<p>Currently, you can get it by doing <code>(μ.prod μ).map fun (f, g) ↦ f ∘ g</code>, where <code>μ : Measure (A → A)</code> is your distribution.</p>",
        "id": 411729514,
        "sender_full_name": "Yaël Dillies",
        "timestamp": 1704717106
    },
    {
        "content": "<p>Note: adding <code>Measure.map₂</code> is <strong>not</strong> on my TODO list. Mostly because the list is already too long.</p>",
        "id": 411747130,
        "sender_full_name": "Yury G. Kudryashov",
        "timestamp": 1704723583
    },
    {
        "content": "<p>If someone else implements it, then I'll be happy to review it.</p>",
        "id": 411747227,
        "sender_full_name": "Yury G. Kudryashov",
        "timestamp": 1704723605
    }
]