[
    {
        "content": "<p>Hi, does mathlib4 api doc builder autolinks files? If yes, then which syntax? <code>Mathlib.Algebra.Group.Basic</code>, <code>Algebra.Group.Basic</code>, or <code>Algebra/Group/Basic</code>?</p>",
        "id": 361830026,
        "sender_full_name": "Yury G. Kudryashov",
        "timestamp": 1685314553
    },
    {
        "content": "<p><span class=\"user-mention\" data-user-id=\"395550\">@Henrik Böving</span> would know</p>",
        "id": 362598635,
        "sender_full_name": "James Gallicchio",
        "timestamp": 1685578382
    },
    {
        "content": "<p>I think we should consider adding a custom syntax for this to ensure that we actually refer to files that exist</p>",
        "id": 362601736,
        "sender_full_name": "Eric Wieser",
        "timestamp": 1685580326
    },
    {
        "content": "<p><a href=\"https://myst-tools.org/\">https://myst-tools.org/</a> does something like this</p>",
        "id": 362601763,
        "sender_full_name": "Eric Wieser",
        "timestamp": 1685580341
    },
    {
        "content": "<p>Yeah, and resolving them in the same way that lake resolves imports seems reasonable. I think there's already an API in lake for doing so.</p>",
        "id": 362605521,
        "sender_full_name": "James Gallicchio",
        "timestamp": 1685582391
    },
    {
        "content": "<p><span class=\"user-mention silent\" data-user-id=\"214703\">Yury G. Kudryashov</span> <a href=\"#narrow/stream/287929-mathlib4/topic/autolinking.20files.20in.20docs/near/361830026\">said</a>:</p>\n<blockquote>\n<p>Hi, does mathlib4 api doc builder autolinks files? If yes, then which syntax? <code>Mathlib.Algebra.Group.Basic</code>, <code>Algebra.Group.Basic</code>, or <code>Algebra/Group/Basic</code>?</p>\n</blockquote>\n<p>If you mean within doc strings then no</p>",
        "id": 362637603,
        "sender_full_name": "Henrik Böving",
        "timestamp": 1685600027
    },
    {
        "content": "<p><span class=\"user-mention silent\" data-user-id=\"395550\">Henrik Böving</span> <a href=\"#narrow/stream/287929-mathlib4/topic/autolinking.20files.20in.20docs/near/362637603\">said</a>:</p>\n<blockquote>\n<p><span class=\"user-mention silent\" data-user-id=\"214703\">Yury G. Kudryashov</span> <a href=\"#narrow/stream/287929-mathlib4/topic/autolinking.20files.20in.20docs/near/361830026\">said</a>:</p>\n<blockquote>\n<p>Hi, does mathlib4 api doc builder autolinks files? If yes, then which syntax? <code>Mathlib.Algebra.Group.Basic</code>, <code>Algebra.Group.Basic</code>, or <code>Algebra/Group/Basic</code>?</p>\n</blockquote>\n<p>If you mean within doc strings then no</p>\n</blockquote>\n<p>Can \"we\" make it so? :)</p>",
        "id": 362650028,
        "sender_full_name": "Ruben Van de Velde",
        "timestamp": 1685603741
    },
    {
        "content": "<p>In theory sure, it would be generally cool if we could agree on some form of markdown based documentation format because right now all of the linking in the docs is on a purely heuristical basis</p>",
        "id": 362658957,
        "sender_full_name": "Henrik Böving",
        "timestamp": 1685606058
    }
]