[
    {
        "content": "<p>Is there a way to have the TC search to not be hit by simp here? You can imagine I had a more complex expression like <code>(k + 0) + l &lt; (l + 0)</code> and wanted simp to simplify it.</p>\n<div class=\"codehilite\" data-code-language=\"Lean\"><pre><span></span><code><span class=\"kn\">import</span> <span class=\"n\">Mathlib.Data.Fin.Basic</span>\n\n<span class=\"kd\">example</span> <span class=\"o\">{</span><span class=\"n\">n</span> <span class=\"o\">:</span> <span class=\"n\">ℕ</span><span class=\"o\">}</span> <span class=\"o\">(</span><span class=\"n\">k</span> <span class=\"n\">l</span> <span class=\"o\">:</span> <span class=\"n\">Fin</span> <span class=\"o\">(</span><span class=\"n\">n</span> <span class=\"bp\">+</span> <span class=\"mi\">1</span><span class=\"o\">))</span> <span class=\"o\">:</span> <span class=\"n\">k</span> <span class=\"bp\">+</span> <span class=\"n\">l</span> <span class=\"bp\">&lt;</span> <span class=\"n\">l</span> <span class=\"o\">:=</span> <span class=\"kd\">by</span>\n  <span class=\"n\">simp</span> <span class=\"c1\">-- times out</span>\n  <span class=\"c1\">-- failed to synthesize</span>\n  <span class=\"c1\">-- CovariantClass (Fin (n + 1)) (Fin (n + 1)) (Function.swap fun x x_1 ↦ x + x_1) fun x x_1 ↦ x &lt; x_1</span>\n  <span class=\"c1\">-- (deterministic) timeout at 'typeclass', maximum number of heartbeats (20000) has been reached (use 'set_option synthInstance.maxHeartbeats &lt;num&gt;' to set the limit)</span>\n</code></pre></div>",
        "id": 410895942,
        "sender_full_name": "Yakov Pechersky",
        "timestamp": 1704224525
    },
    {
        "content": "<p>We could remove <code>CovarianatClass</code>...</p>",
        "id": 410904162,
        "sender_full_name": "Kevin Buzzard",
        "timestamp": 1704228745
    },
    {
        "content": "<p>Agreed</p>",
        "id": 410904228,
        "sender_full_name": "Yaël Dillies",
        "timestamp": 1704228799
    }
]