[
    {
        "content": "<div class=\"codehilite\" data-code-language=\"Lean4\"><pre><span></span><code><span class=\"kn\">def</span><span class=\"w\"> </span><span class=\"n\">main</span><span class=\"w\"> </span><span class=\"o\">:</span><span class=\"w\"> </span><span class=\"n\">IO</span><span class=\"w\"> </span><span class=\"n\">Unit</span><span class=\"w\"> </span><span class=\"o\">:=</span>\n<span class=\"w\">  </span><span class=\"k\">let</span><span class=\"w\"> </span><span class=\"bp\">_</span><span class=\"w\"> </span><span class=\"o\">:=</span><span class=\"w\"> </span><span class=\"n\">IO</span><span class=\"bp\">.</span><span class=\"n\">println</span><span class=\"w\"> </span><span class=\"s2\">\"teste\"</span>\n<span class=\"w\">  </span><span class=\"k\">let</span><span class=\"w\"> </span><span class=\"bp\">_</span><span class=\"w\"> </span><span class=\"o\">:=</span><span class=\"w\"> </span><span class=\"n\">IO</span><span class=\"bp\">.</span><span class=\"n\">FS</span><span class=\"bp\">.</span><span class=\"n\">writeFile</span><span class=\"w\"> </span><span class=\"o\">(</span><span class=\"n\">System</span><span class=\"bp\">.</span><span class=\"n\">FilePath</span><span class=\"bp\">.</span><span class=\"n\">mk</span><span class=\"w\"> </span><span class=\"s2\">\"test1.txt\"</span><span class=\"o\">)</span><span class=\"w\"> </span><span class=\"s2\">\"test 1\"</span>\n<span class=\"w\">  </span><span class=\"k\">let</span><span class=\"w\"> </span><span class=\"bp\">_</span><span class=\"w\"> </span><span class=\"o\">:=</span><span class=\"w\"> </span><span class=\"n\">IO</span><span class=\"bp\">.</span><span class=\"n\">FS</span><span class=\"bp\">.</span><span class=\"n\">writeFile</span><span class=\"w\"> </span><span class=\"o\">(</span><span class=\"n\">System</span><span class=\"bp\">.</span><span class=\"n\">FilePath</span><span class=\"bp\">.</span><span class=\"n\">mk</span><span class=\"w\"> </span><span class=\"s2\">\"test2.txt\"</span><span class=\"o\">)</span><span class=\"w\"> </span><span class=\"s2\">\"test 2\"</span>\n<span class=\"w\">  </span><span class=\"n\">return</span><span class=\"w\"> </span><span class=\"o\">()</span>\n</code></pre></div>\n<p>How to make that code to really execute the IO operations? It may be related to the <code>IO.RealWord</code>, but I didn't really understand it. Any idea?</p>",
        "id": 485014827,
        "sender_full_name": "Alexandre Rademaker",
        "timestamp": 1732850670
    },
    {
        "content": "<p><a href=\"https://leanprover-community.github.io/mathlib4_docs/find/?pattern=IO.FS.writeFile#doc\">docs#IO.FS.writeFile</a></p>",
        "id": 485015667,
        "sender_full_name": "Adam Topaz",
        "timestamp": 1732851323
    },
    {
        "content": "<p>If you replace the last three <code>:=</code> with <code>&lt;-</code> then it should work</p>",
        "id": 485015740,
        "sender_full_name": "Adam Topaz",
        "timestamp": 1732851375
    },
    {
        "content": "<p>Oh and add a <code>do</code> after the first <code>:=</code></p>",
        "id": 485015761,
        "sender_full_name": "Adam Topaz",
        "timestamp": 1732851396
    },
    {
        "content": "<p>You don’t even have to use <code>let _ …</code> when you have something of type <code>IO Unit</code></p>",
        "id": 485015812,
        "sender_full_name": "Adam Topaz",
        "timestamp": 1732851461
    },
    {
        "content": "<p>This might help: <a href=\"https://lean-lang.org/functional_programming_in_lean/monads/do.html\">https://lean-lang.org/functional_programming_in_lean/monads/do.html</a></p>",
        "id": 485015919,
        "sender_full_name": "Adam Topaz",
        "timestamp": 1732851542
    },
    {
        "content": "<p>Oh... I forgot the <code>do</code>! Sorry about that!</p>",
        "id": 485016994,
        "sender_full_name": "Alexandre Rademaker",
        "timestamp": 1732852436
    },
    {
        "content": "<p><span class=\"user-mention silent\" data-user-id=\"121542\">Alexandre Rademaker</span> has marked this topic as resolved.</p>",
        "id": 485017068,
        "sender_full_name": "Notification Bot",
        "timestamp": 1732852479
    }
]