[
    {
        "content": "<p>The call for papers for CPP '21 (Certified Programs and Proofs) is out! <a href=\"https://popl21.sigplan.org/home/CPP-2021#Call-for-Papers\" title=\"https://popl21.sigplan.org/home/CPP-2021#Call-for-Papers\">https://popl21.sigplan.org/home/CPP-2021#Call-for-Papers</a><br>\nWe hope some of the Lean Zulip crowd will consider submitting.</p>",
        "id": 194451829,
        "sender_full_name": "Rob Lewis",
        "timestamp": 1587135071
    },
    {
        "content": "<p>Note that the abstract deadline is September 16, earlier than in past years.</p>",
        "id": 194451876,
        "sender_full_name": "Rob Lewis",
        "timestamp": 1587135088
    },
    {
        "content": "<p>Would they consider a paper about schemes?</p>",
        "id": 194455606,
        "sender_full_name": "Kevin Buzzard",
        "timestamp": 1587136369
    },
    {
        "content": "<p>Does it contain programs and/or proofs? <span aria-label=\"upside down\" class=\"emoji emoji-1f643\" role=\"img\" title=\"upside down\">:upside_down:</span></p>",
        "id": 194456413,
        "sender_full_name": "Reid Barton",
        "timestamp": 1587136635
    },
    {
        "content": "<p><span class=\"user-mention silent\" data-user-id=\"110032\">Reid Barton</span> <a href=\"#narrow/stream/113488-general/topic/CPP.20'21/near/194456413\" title=\"#narrow/stream/113488-general/topic/CPP.20'21/near/194456413\">said</a>:</p>\n<blockquote>\n<p>Does it contain programs and/or proofs? <span aria-label=\"upside down\" class=\"emoji emoji-1f643\" role=\"img\" title=\"upside down\">:upside_down:</span></p>\n</blockquote>\n<p>And are they certified? If so, submit!</p>",
        "id": 194456486,
        "sender_full_name": "Rob Lewis",
        "timestamp": 1587136663
    }
]