[
    {
        "content": "<p>run \"lake build\" gets \"error: toolchain 'leanprover/lean4:v4.9.0-rc1' is not installed\", how to resolve it?</p>",
        "id": 485432877,
        "sender_full_name": "Shuffle",
        "timestamp": 1733013261
    },
    {
        "content": "<p>What is <code>type -a lake</code> and how did you install elan?</p>",
        "id": 485433071,
        "sender_full_name": "Julian Berman",
        "timestamp": 1733013488
    },
    {
        "content": "<p><a href=\"/user_uploads/3121/_WTVl6X-cfMhcP9pK4Obi5Ye/image.png\">image.png</a></p>\n<div class=\"message_inline_image\"><a href=\"/user_uploads/3121/_WTVl6X-cfMhcP9pK4Obi5Ye/image.png\" title=\"image.png\"><img data-original-dimensions=\"1152x358\" src=\"/user_uploads/thumbnail/3121/_WTVl6X-cfMhcP9pK4Obi5Ye/image.png/840x560.webp\"></a></div>",
        "id": 485433122,
        "sender_full_name": "Shuffle",
        "timestamp": 1733013569
    },
    {
        "content": "<p><span class=\"user-mention silent\" data-user-id=\"321696\">Julian Berman</span> <a href=\"#narrow/channel/113488-general/topic/Install.20help.20needed/near/485433071\">发言道</a>：</p>\n<blockquote>\n<p>What is <code>type -a lake</code> and how did you install elan?</p>\n</blockquote>\n<p>and i should installed elan use the default vscode extension</p>",
        "id": 485433200,
        "sender_full_name": "Shuffle",
        "timestamp": 1733013627
    },
    {
        "content": "<p><a href=\"/user_uploads/3121/JZ5DNovQq2sna91hSrb-KJHR/image.png\">image.png</a><br>\nI already have stable and 4.7.0 installed in .elan/toolchains</p>\n<div class=\"message_inline_image\"><a href=\"/user_uploads/3121/JZ5DNovQq2sna91hSrb-KJHR/image.png\" title=\"image.png\"><img data-original-dimensions=\"956x82\" src=\"/user_uploads/thumbnail/3121/JZ5DNovQq2sna91hSrb-KJHR/image.png/840x560.webp\"></a></div><p>I am curious that we can install only two versions of lean? Or indeed more than two</p>",
        "id": 485433249,
        "sender_full_name": "Shuffle",
        "timestamp": 1733013704
    },
    {
        "content": "<p><span class=\"user-mention silent\" data-user-id=\"784329\">Shuffle</span> <a href=\"#narrow/channel/113488-general/topic/Install.20help.20needed/near/485433249\">said</a>:</p>\n<blockquote>\n<p><a href=\"/user_uploads/3121/JZ5DNovQq2sna91hSrb-KJHR/image.png\">image.png</a><br>\nI already have stable and 4.7.0 installed in .elan/toolchains</p>\n<p>I am curious that we can install only two versions of lean? Or indeed more than two</p>\n</blockquote>\n<p>That's essentially the entire purpose of <code>elan</code>, yeah -- so something strange is happening.</p>",
        "id": 485433501,
        "sender_full_name": "Julian Berman",
        "timestamp": 1733013979
    },
    {
        "content": "<p>What does <code>elan toolchain install 4.9.0-rc1</code> say?</p>",
        "id": 485433519,
        "sender_full_name": "Julian Berman",
        "timestamp": 1733014009
    },
    {
        "content": "<p><a href=\"/user_uploads/3121/sLeFOMyeWb7CtTX3-I6H6h7w/image.png\">image.png</a></p>\n<div class=\"message_inline_image\"><a href=\"/user_uploads/3121/sLeFOMyeWb7CtTX3-I6H6h7w/image.png\" title=\"image.png\"><img data-original-dimensions=\"1414x140\" src=\"/user_uploads/thumbnail/3121/sLeFOMyeWb7CtTX3-I6H6h7w/image.png/840x560.webp\"></a></div>",
        "id": 485433556,
        "sender_full_name": "Shuffle",
        "timestamp": 1733014079
    },
    {
        "content": "<p><a href=\"/user_uploads/3121/Bj860FYbd7bFZReL3JHY5FbL/image.png\">image.png</a><br>\nActually this works</p>\n<div class=\"message_inline_image\"><a href=\"/user_uploads/3121/Bj860FYbd7bFZReL3JHY5FbL/image.png\" title=\"image.png\"><img data-original-dimensions=\"1590x176\" src=\"/user_uploads/thumbnail/3121/Bj860FYbd7bFZReL3JHY5FbL/image.png/840x560.webp\"></a></div>",
        "id": 485433614,
        "sender_full_name": "Shuffle",
        "timestamp": 1733014118
    },
    {
        "content": "<p>Yes, you left off the <code>toolchain</code> in the first one.</p>",
        "id": 485433722,
        "sender_full_name": "Julian Berman",
        "timestamp": 1733014227
    },
    {
        "content": "<p>And now does <code>lake build</code> work?</p>",
        "id": 485433729,
        "sender_full_name": "Julian Berman",
        "timestamp": 1733014232
    },
    {
        "content": "<p>Also what's <code>elan --version</code>?</p>",
        "id": 485433730,
        "sender_full_name": "Julian Berman",
        "timestamp": 1733014237
    },
    {
        "content": "<p><code>elan --version</code> is <code>elan 3.1.1 (71ddc6633 2024-02-22)</code>, and <code>lake build</code> works now.</p>",
        "id": 485433753,
        "sender_full_name": "Shuffle",
        "timestamp": 1733014281
    },
    {
        "content": "<p>Thanks a lot. I am a bit confused by how elan works, just as you see i forget the <code>toolchain</code>, I cannot find detailed document for elan</p>",
        "id": 485433827,
        "sender_full_name": "Shuffle",
        "timestamp": 1733014326
    },
    {
        "content": "<p>That looks right. I'm confused as to why your <code>lake</code> didn't install the toolchain automatically, as that's what the wrapper is meant for. Your PATH looks a bit screwy (as evidenced by seeing the same directory 10 times or whatever) but that shouldn't affect things.</p>",
        "id": 485434457,
        "sender_full_name": "Julian Berman",
        "timestamp": 1733015018
    },
    {
        "content": "<p>I actually don't know where longer docs for <code>elan</code> live either now that I think about it, if they do live somewhere. There seems to be no man page. Eventually it will live here: <a href=\"https://lean-lang.org/doc/reference/latest/Elan/#elan\">https://lean-lang.org/doc/reference/latest/Elan/#elan</a> but the page is a TODO right now.</p>",
        "id": 485434664,
        "sender_full_name": "Julian Berman",
        "timestamp": 1733015200
    },
    {
        "content": "<p><code>elan --help</code> will have at least basic information.</p>",
        "id": 485434674,
        "sender_full_name": "Julian Berman",
        "timestamp": 1733015214
    },
    {
        "content": "<p>thanks a lot. I think they will have a document later, but for now let me just use the <code>elan --help</code></p>",
        "id": 485435014,
        "sender_full_name": "Shuffle",
        "timestamp": 1733015548
    },
    {
        "content": "<p>Most of the point is you really shouldn't have to interact with elan at all, so the \"real problem\" is if <code>lake build</code> is not automatically installing toolchains for you. If it happens again I think we try to figure out why.</p>",
        "id": 485435940,
        "sender_full_name": "Julian Berman",
        "timestamp": 1733016476
    }
]