[
    {
        "content": "<p>Hi! I found out that we only allow absolutely convergent series in lean. I'm curious about how should I define an infinite sum that it only convergent under some order of sum? For example, the infinite sum (-1)^n *(1/n) over positive natural number.</p>",
        "id": 535371351,
        "sender_full_name": "Chengyan Hu",
        "timestamp": 1755715478
    },
    {
        "content": "<p>It sounds like if we are summing over a set with order like N, we are able to talk about conditional convergent?</p>",
        "id": 535372760,
        "sender_full_name": "Chengyan Hu",
        "timestamp": 1755716099
    },
    {
        "content": "<p>See <a class=\"stream-topic\" data-stream-id=\"287929\" href=\"/#narrow/channel/287929-mathlib4/topic/Conditionally.20convergent.20series/with/488009787\">#mathlib4 &gt; Conditionally convergent series</a></p>",
        "id": 535372996,
        "sender_full_name": "Aaron Liu",
        "timestamp": 1755716212
    }
]