[
    {
        "content": "<p>I'm stuck on this, because my brain doesn't work today. I'm trying to find better proof, if possible.</p>\n<div class=\"codehilite\" data-code-language=\"Lean4\"><pre><span></span><code><span class=\"kn\">import</span><span class=\"w\"> </span><span class=\"n\">Mathlib</span>\n\n<span class=\"kn\">theorem</span><span class=\"w\"> </span><span class=\"n\">THM</span><span class=\"w\"> </span><span class=\"o\">(</span><span class=\"n\">x</span><span class=\"o\">:</span><span class=\"w\"> </span><span class=\"n\">ℕ</span><span class=\"o\">)</span><span class=\"w\"> </span><span class=\"o\">(</span><span class=\"n\">Hx</span><span class=\"o\">:</span><span class=\"w\"> </span><span class=\"n\">x</span><span class=\"w\"> </span><span class=\"bp\">≠</span><span class=\"w\"> </span><span class=\"mi\">0</span><span class=\"o\">):</span><span class=\"w\"> </span><span class=\"n\">x</span><span class=\"w\"> </span><span class=\"bp\">=</span><span class=\"w\"> </span><span class=\"o\">(</span><span class=\"bp\">∏</span><span class=\"w\"> </span><span class=\"n\">i</span><span class=\"w\"> </span><span class=\"bp\">∈</span><span class=\"w\"> </span><span class=\"n\">x</span><span class=\"bp\">.</span><span class=\"n\">primeFactors</span><span class=\"o\">,</span><span class=\"w\"> </span><span class=\"n\">i</span><span class=\"w\"> </span><span class=\"bp\">^</span><span class=\"w\"> </span><span class=\"o\">(</span><span class=\"n\">x</span><span class=\"bp\">.</span><span class=\"n\">factorization</span><span class=\"w\"> </span><span class=\"n\">i</span><span class=\"o\">))</span><span class=\"w\"> </span><span class=\"o\">:=</span><span class=\"w\"> </span><span class=\"k\">by</span>\n<span class=\"w\">  </span><span class=\"k\">have</span><span class=\"w\"> </span><span class=\"n\">H</span><span class=\"w\"> </span><span class=\"o\">:=</span><span class=\"w\"> </span><span class=\"n\">Nat</span><span class=\"bp\">.</span><span class=\"n\">prod_pow_factorization_eq_self</span><span class=\"w\"> </span><span class=\"o\">(</span><span class=\"n\">f</span><span class=\"w\"> </span><span class=\"o\">:=</span><span class=\"w\"> </span><span class=\"n\">x</span><span class=\"bp\">.</span><span class=\"n\">factorization</span><span class=\"o\">)</span>\n<span class=\"w\">  </span><span class=\"k\">have</span><span class=\"w\"> </span><span class=\"n\">H0</span><span class=\"w\"> </span><span class=\"o\">:=</span><span class=\"w\"> </span><span class=\"n\">H</span><span class=\"w\"> </span><span class=\"o\">(</span><span class=\"k\">fun</span><span class=\"w\"> </span><span class=\"n\">p</span><span class=\"w\"> </span><span class=\"n\">Hp</span><span class=\"w\"> </span><span class=\"bp\">=&gt;</span><span class=\"w\"> </span><span class=\"n\">Nat</span><span class=\"bp\">.</span><span class=\"n\">prime_of_mem_primeFactors</span><span class=\"w\"> </span><span class=\"n\">Hp</span><span class=\"o\">)</span>\n<span class=\"w\">  </span><span class=\"k\">have</span><span class=\"w\"> </span><span class=\"n\">H1</span><span class=\"w\"> </span><span class=\"o\">:=</span><span class=\"w\"> </span><span class=\"n\">Nat</span><span class=\"bp\">.</span><span class=\"n\">factorization_inj</span>\n<span class=\"w\">  </span><span class=\"n\">apply</span><span class=\"w\"> </span><span class=\"n\">H1</span><span class=\"w\"> </span><span class=\"k\">at</span><span class=\"w\"> </span><span class=\"n\">H0</span>\n<span class=\"w\">  </span><span class=\"bp\">.</span><span class=\"w\"> </span><span class=\"n\">simp</span><span class=\"w\"> </span><span class=\"o\">[</span><span class=\"n\">Finsupp</span><span class=\"bp\">.</span><span class=\"n\">prod</span><span class=\"o\">]</span><span class=\"w\"> </span><span class=\"k\">at</span><span class=\"w\"> </span><span class=\"n\">H0</span>\n<span class=\"w\">    </span><span class=\"n\">exact</span><span class=\"w\"> </span><span class=\"n\">H0</span><span class=\"bp\">.</span><span class=\"n\">symm</span>\n<span class=\"w\">  </span><span class=\"bp\">.</span><span class=\"w\"> </span><span class=\"n\">simp</span>\n<span class=\"w\">    </span><span class=\"n\">intros</span><span class=\"w\"> </span><span class=\"n\">p</span><span class=\"w\"> </span><span class=\"n\">Hp</span><span class=\"w\"> </span><span class=\"n\">H0</span><span class=\"w\"> </span><span class=\"n\">H1</span><span class=\"w\"> </span><span class=\"n\">h2</span>\n<span class=\"w\">    </span><span class=\"n\">subst</span><span class=\"w\"> </span><span class=\"n\">p</span>\n<span class=\"w\">    </span><span class=\"n\">omega</span>\n<span class=\"w\">  </span><span class=\"bp\">.</span><span class=\"w\"> </span><span class=\"n\">simp</span>\n<span class=\"w\">    </span><span class=\"n\">exact</span><span class=\"w\"> </span><span class=\"n\">Hx</span>\n</code></pre></div>\n<p>Thanks for any hints!</p>",
        "id": 519145962,
        "sender_full_name": "Ilmārs Cīrulis",
        "timestamp": 1747668173
    },
    {
        "content": "<p>I had just asked about the prime factorization recently. learnt this thanks to Yaël Dillies.</p>\n<div class=\"codehilite\" data-code-language=\"Lean\"><pre><span></span><code><span class=\"kn\">import</span><span class=\"w\"> </span><span class=\"n\">Mathlib</span>\n\n<span class=\"kd\">theorem</span><span class=\"w\"> </span><span class=\"n\">THM</span><span class=\"w\"> </span><span class=\"o\">(</span><span class=\"n\">x</span><span class=\"o\">:</span><span class=\"w\"> </span><span class=\"n\">ℕ</span><span class=\"o\">)</span><span class=\"w\"> </span><span class=\"o\">(</span><span class=\"n\">Hx</span><span class=\"o\">:</span><span class=\"w\"> </span><span class=\"n\">x</span><span class=\"w\"> </span><span class=\"bp\">≠</span><span class=\"w\"> </span><span class=\"mi\">0</span><span class=\"o\">):</span><span class=\"w\"> </span><span class=\"n\">x</span><span class=\"w\"> </span><span class=\"bp\">=</span><span class=\"w\"> </span><span class=\"o\">(</span><span class=\"bp\">∏</span><span class=\"w\"> </span><span class=\"n\">i</span><span class=\"w\"> </span><span class=\"bp\">∈</span><span class=\"w\"> </span><span class=\"n\">x.primeFactors</span><span class=\"o\">,</span><span class=\"w\"> </span><span class=\"n\">i</span><span class=\"w\"> </span><span class=\"bp\">^</span><span class=\"w\"> </span><span class=\"o\">(</span><span class=\"n\">x.factorization</span><span class=\"w\"> </span><span class=\"n\">i</span><span class=\"o\">))</span><span class=\"w\"> </span><span class=\"o\">:=</span>\n<span class=\"w\">   </span><span class=\"o\">(</span><span class=\"n\">Nat.factorization_prod_pow_eq_self</span><span class=\"w\"> </span><span class=\"n\">Hx</span><span class=\"o\">)</span><span class=\"bp\">.</span><span class=\"n\">symm</span>\n</code></pre></div>",
        "id": 519147108,
        "sender_full_name": "Sabbir Rahman",
        "timestamp": 1747668434
    },
    {
        "content": "<p>Thank you very much!</p>",
        "id": 519147702,
        "sender_full_name": "Ilmārs Cīrulis",
        "timestamp": 1747668560
    }
]